{
  "required": true,
  "package": "com.abdelaziz.saturn.mixin",
  "compatibilityLevel": "JAVA_17",
  "minVersion": "0.8.2",
  "refmap": "saturn.refmap.json",
  "plugin": "com.abdelaziz.saturn.mixin.SaturnMixinPlugin",
  "injectors": {
    "defaultRequire": 1
  },
  "mixins": [
    "ai.brain.clear_memories.BrainMixin",
    "ai.brain.clear_memories.LivingEntityMixin",
    "miscellaneous.strong_interner.TagKeyMixin",
    "world.temperature_cache.BiomeMixin"
  ],
  "client": [
    "miscellaneous.read_resource.TextureUtilMixin"
  ]
}
